biolect/__init__.py
biolect/core/__init__.py
biolect/core/dtypes.py
biolect/core/operations.py
biolect/core/pipeline.py
biolect/core/validation.py
biolect/core/definitions/__init__.py
biolect/core/errors/__init__.py
biolect/core/errors/etypes.py
biolect/core/errors/handlers.py
biolect/core/errors/monadic.py
biolect/core/errors/recovery.py
biolect/formats/fasta.py
biolect/formats/fastq.py
biolect/formats/gff.py
biolect/formats/phylip.py
biolect/formats/sambam.py
biolect/formats/vcf.py
biolect/formats/parsers/__init__.py
biolect/formats/parsers/safe_parsers.py
biolect/formats/parsers/validators.py
biolect/integrations/__init__.py
biolect/integrations/blast.py
biolect/integrations/clustal.py
biolect/integrations/external.py
biolect/integrations/muscle.py
biolect/integrations/raxml.py
biolect/integrations/safe/__init__.py
biolect/integrations/safe/blast_safe.py
biolect/integrations/safe/tools_safe.py
biolect/operations/__init__.py
biolect/operations/alignment/__init__.py
biolect/operations/alignment/consensus.py
biolect/operations/alignment/multiple.py
biolect/operations/alignment/pairwise.py
biolect/operations/alignment/safe/__init__.py
biolect/operations/alignment/safe/monadic_ops.py
biolect/operations/analysis/__init__.py
biolect/operations/analysis/clustering.py
biolect/operations/analysis/quality.py
biolect/operations/analysis/statistics.py
biolect/operations/analysis/visualization.py
biolect/operations/analysis/safe/__init__.py
biolect/operations/analysis/safe/monadic_ops.py
biolect/operations/annotation/__init__.py
biolect/operations/annotation/comparative.py
biolect/operations/annotation/functional.py
biolect/operations/annotation/gene_calling.py
biolect/operations/annotation/safe/__init__.py
biolect/operations/annotation/safe/monadic_ops.py
biolect/operations/phylogenetics/__init__.py
biolect/operations/phylogenetics/distance.py
biolect/operations/phylogenetics/trees.py
biolect/operations/phylogenetics/visualization.py
biolect-0.0.0.dev1.dist-info/METADATA
biolect-0.0.0.dev1.dist-info/WHEEL
biolect-0.0.0.dev1.dist-info/licenses/LICENSE
biolect-0.0.0.dev1.dist-info/RECORD
