Metadata-Version: 2.4
Name: biolect
Version: 0.0.0.dev1
Summary: An embedded bioinformatics DSL framework.
Author-email: "K. LeBryce" <k.lebryce@pm.me>
License-File: LICENSE
Requires-Python: >=3.11
Requires-Dist: biopython>=1.85
Requires-Dist: matplotlib>=3.10.3
Requires-Dist: numpy>=2.2.6
Requires-Dist: pandas>=2.2.3
Requires-Dist: polars>=1.30.0
Requires-Dist: python-dotenv>=1.1.0
Requires-Dist: returns>=0.25.0
Requires-Dist: scipy>=1.15.3
Requires-Dist: seaborn>=0.13.2
Requires-Dist: sympy>=1.14.0
